Metadata-Version: 2.1
Name: tfserving-grpc-helper
Version: 2.4.1
Summary: personal lib
Home-page: https://github.com/genggui001/tfserving_grpc_helper
Author: genggui001
Author-email: genggui001@gmail.com
Classifier: Programming Language :: Python :: 3
Classifier: License :: OSI Approved :: MIT License
Classifier: Operating System :: OS Independent
Requires-Python: >=3.6
License-File: LICENSE
